tiramisu/__init__.py
tiramisu/api.py
tiramisu/autolib.py
tiramisu/cacheobj.py
tiramisu/config.py
tiramisu/error.py
tiramisu/function.py
tiramisu/i18n.py
tiramisu/log.py
tiramisu/setting.py
tiramisu/todict.py
tiramisu/value.py
tiramisu/locale/fr/LC_MESSAGES/tiramisu.mo
tiramisu/option/__init__.py
tiramisu/option/baseoption.py
tiramisu/option/booloption.py
tiramisu/option/broadcastoption.py
tiramisu/option/choiceoption.py
tiramisu/option/dateoption.py
tiramisu/option/domainnameoption.py
tiramisu/option/dynoptiondescription.py
tiramisu/option/emailoption.py
tiramisu/option/filenameoption.py
tiramisu/option/floatoption.py
tiramisu/option/intoption.py
tiramisu/option/ipoption.py
tiramisu/option/leadership.py
tiramisu/option/macoption.py
tiramisu/option/netmaskoption.py
tiramisu/option/networkoption.py
tiramisu/option/option.py
tiramisu/option/optiondescription.py
tiramisu/option/passwordoption.py
tiramisu/option/permissionsoption.py
tiramisu/option/portoption.py
tiramisu/option/stroption.py
tiramisu/option/symlinkoption.py
tiramisu/option/urloption.py
tiramisu/option/usernameoption.py
tiramisu-5.1.0.dist-info/COPYING
tiramisu-5.1.0.dist-info/LICENSE
tiramisu-5.1.0.dist-info/WHEEL
tiramisu-5.1.0.dist-info/METADATA
tiramisu-5.1.0.dist-info/RECORD
